{"hotels": [{"name": "THE WESTGATE HOTEL", "address": {"lines": ["1055 SECOND AVENUE"], "postalCode": "92101", "cityName": "SAN DIEGO", "countryCode": "US", "stateCode": "CA"}, "stars": "4"}, {"name": "COURTYARD DOWNTOWN MARRIOTT", "address": {"lines": ["530 BROADWAY"], "postalCode": "92101", "cityName": "SAN DIEGO", "countryCode": "US", "stateCode": "CA"}, "stars": "4"}, {"name": "HOLIDAY INN EXPRESS DOWNTOWN", "address": {"lines": ["1430 7TH AVE"], "postalCode": "921011", "cityName": "SAN DIEGO", "countryCode": "US", "stateCode": "CA"}, "stars": "2"}, {"name": "HORTON GRAND HOTEL", "address": {"lines": ["311 ISLAND AVENUE"], "postalCode": "92101", "cityName": "SAN DIEGO", "countryCode": "US", "stateCode": "CA"}, "stars": "3"}, {"name": "BEST WESTERN PLUS BAYSIDE INN", "address": {"lines": ["555 W ASH STREET"], "postalCode": "92101", "cityName": "SAN DIEGO", "countryCode": "US", "stateCode": "CA"}, "stars": "2"}, {"name": "FOUR POINTS SAN DIEGO DWNTWN", "address": {"lines": ["1617  FIRST AVENUE"], "postalCode": "92101", "cityName": "SAN DIEGO", "countryCode": "US", "stateCode": "CA"}, "stars": "2"}, {"name": "RESIDENCE INN GASLAMP MARRIOTT", "address": {"lines": ["356 6TH AVENUE"], "postalCode": "92101", "cityName": "SAN DIEGO", "countryCode": "US", "stateCode": "CA"}, "stars": "4"}, {"name": "HAMPTON INN SAN DIEGO DWNTWN", "address": {"lines": ["1531 PACIFIC HWY"], "postalCode": "92101", "cityName": "SAN DIEGO", "countryCode": "US", "stateCode": "CA"}, "stars": "2"}, {"name": "RESIDENCE INN DOWNTWN MARRIOTT", "address": {"lines": ["1747 PACIFIC HIGHWAY"], "postalCode": "92101", "cityName": "SAN DIEGO", "countryCode": "US", "stateCode": "CA"}, "stars": "4"}, {"name": "Sheraton San Diego Hotel & Marina", "address": {"lines": ["1380 HARBOR ISLAND DRIVE"], "postalCode": "92101", "cityName": "SAN DIEGO", "countryCode": "US", "stateCode": "CA"}, "stars": "4"}, {"name": "HOLIDAY INN EXP ARPT OLD TOWN", "address": {"lines": ["1955 SAN DIEGO AVENUE"], "postalCode": "92110", "cityName": "SAN DIEGO", "countryCode": "US", "stateCode": "CA"}, "stars": "2"}, {"name": "COURTYARD OLD TOWN MARRIOTT", "address": {"lines": ["2435 JEFFERSON ST"], "postalCode": "92110", "cityName": "SAN DIEGO", "countryCode": "US", "stateCode": "CA"}, "stars": "4"}, {"name": "COURTYARD MISSION VLY MARRIOTT", "address": {"lines": ["595 HOTEL CIRCLE SOUTH"], "postalCode": "92108", "cityName": "SAN DIEGO", "countryCode": "US", "stateCode": "CA"}, "stars": "4"}, {"name": "RESIDENCE INN MISSION MARRIOTT", "address": {"lines": ["1865 HOTEL CIRCLE SOUTH"], "postalCode": "92108", "cityName": "SAN DIEGO", "countryCode": "US", "stateCode": "CA"}, "stars": "4"}, {"name": "Holiday Inn Exp Stes Hotel Circle", "address": {"lines": ["635 HOTEL CIRCLE SOUTH"], "postalCode": "92108", "cityName": "SAN DIEGO", "countryCode": "US", "stateCode": "CA"}, "stars": "2"}, {"name": "HAMPTON INN SAN DIEGO MV", "address": {"lines": ["2151 HOTEL CIRCLE SOUTH"], "postalCode": "92108", "cityName": "SAN DIEGO", "countryCode": "US", "stateCode": "CA"}, "stars": "2"}, {"name": "COURTYARD MARRIOTT SD AIRPORT", "address": {"lines": ["2592 LANING ROAD"], "postalCode": "92106", "cityName": "SAN DIEGO", "countryCode": "US", "stateCode": "CA"}, "stars": "4"}]}